Database/Database.py
Database/__init__.py
Database/es/ElasticSearchClient.py
Database/es/__init__.py
Database/es/es_utils.py
Database/mysql/MysqlClient.py
Database/mysql/__init__.py
esandmysqlconnector-0.1.2.dist-info/METADATA
esandmysqlconnector-0.1.2.dist-info/RECORD
esandmysqlconnector-0.1.2.dist-info/WHEEL
esandmysqlconnector-0.1.2.dist-info/top_level.txt
