Metadata-Version: 1.1
Name: esandmysqlconnector
Version: 0.1.2
Summary: A database setup for es and mysql clients
Home-page: UNKNOWN
Author: Coffeebeans
Author-email: UNKNOWN
License: UNKNOWN
Platform: UNKNOWN
Classifier: Programming Language :: Python :: 3
Classifier: License :: OSI Approved :: MIT License
Classifier: Operating System :: OS Independent
